PhAI/__init__.py
phai-0.0.0.dist-info/licenses/LICENSE
phai-0.0.0.dist-info/METADATA
phai-0.0.0.dist-info/WHEEL
phai-0.0.0.dist-info/top_level.txt
phai-0.0.0.dist-info/RECORD
