Metadata-Version: 2.4
Name: PhAI
Version: 0.0.0
Summary: PhAI
Requires-Python: >=3.8
License-File: LICENSE
Dynamic: license-file
